TransMCL/__init__.py
TransMCL/__main__.py
TransMCL/algorithms.py
TransMCL/alignment.py
TransMCL/assemble_status.py
TransMCL/deal_msa.py
TransMCL/draw_network.py
TransMCL/evaluate.py
TransMCL/evaluate_HOG.py
TransMCL/graph.py
TransMCL/interval.py
TransMCL/isosvm.py
TransMCL/load_data.py
TransMCL/merge_gene.py
TransMCL/multiShell.py
TransMCL/network.py
TransMCL/nwk.py
TransMCL/options.py
TransMCL/species_gene.py
TransMCL/sub.py
TransMCL-1.0.0.dist-info/LICENSE
TransMCL-1.0.0.dist-info/METADATA
TransMCL-1.0.0.dist-info/WHEEL
TransMCL-1.0.0.dist-info/top_level.txt
TransMCL-1.0.0.dist-info/RECORD
